pynsi/Measurement.py
pynsi/__init__.py
pynsi-0.4.4.dist-info/licenses/LICENSE
pynsi-0.4.4.dist-info/METADATA
pynsi-0.4.4.dist-info/WHEEL
pynsi-0.4.4.dist-info/top_level.txt
pynsi-0.4.4.dist-info/RECORD
