Metadata-Version: 2.4
Name: pynsi
Version: 0.4.4
Summary: NSI2000 Professional Antenna Measurement Software Automation Module
Home-page: https://github.com/yigithsyn/pynsi
Author: Hüseyin YİĞİT
Author-email: yigit.hsyn@gmail.com
License: CC BY-NC-SA 4.0
Platform: Any
Classifier: Development Status :: 2 - Pre-Alpha
Classifier: Operating System :: OS Independent
Classifier: Programming Language :: Python
Classifier: Programming Language :: Python :: 3
Classifier: Intended Audience :: Science/Research
Classifier: Topic :: Scientific/Engineering
Classifier: Topic :: Scientific/Engineering :: Mathematics
Classifier: Topic :: Scientific/Engineering :: Physics
Requires-Python: >= 3.4
License-File: LICENSE
Requires-Dist: pywin32==308
Dynamic: author
Dynamic: author-email
Dynamic: classifier
Dynamic: description
Dynamic: description-content-type
Dynamic: home-page
Dynamic: license
Dynamic: license-file
Dynamic: platform
Dynamic: requires-dist
Dynamic: requires-python
Dynamic: summary
